hhsqllib/__init__.py
hhsqllib/corefunc.py
hhsqllib/dbconvert.py
hhsqllib/sqlalgo.py
hhsqllib/sqlconnect.py
hhsqllib/sqlfile.py
hhsqllib/test.py
hhsqllib-0.58.dist-info/METADATA
hhsqllib-0.58.dist-info/WHEEL
hhsqllib-0.58.dist-info/top_level.txt
hhsqllib-0.58.dist-info/RECORD
